sat_pubsub/VERSION
sat_pubsub/__init__.py
sat_pubsub/backend.py
sat_pubsub/const.py
sat_pubsub/container.py
sat_pubsub/delegation.py
sat_pubsub/error.py
sat_pubsub/exceptions.py
sat_pubsub/iidavoll.py
sat_pubsub/mam.py
sat_pubsub/pgsql_storage.py
sat_pubsub/privilege.py
sat_pubsub/pubsub_admin.py
sat_pubsub/test/__init__.py
sat_pubsub/test/test_backend.py
sat_pubsub/test/test_storage.py
sat_pubsub-0.4.0.data/data/share/doc/sat_pubsub/CHANGELOG
sat_pubsub-0.4.0.data/data/share/doc/sat_pubsub/COPYING
sat_pubsub-0.4.0.data/data/share/doc/sat_pubsub/README
twisted/plugins/pubsub.py
sat_pubsub-0.4.0.dist-info/COPYING
sat_pubsub-0.4.0.dist-info/METADATA
sat_pubsub-0.4.0.dist-info/WHEEL
sat_pubsub-0.4.0.dist-info/top_level.txt
sat_pubsub-0.4.0.dist-info/zip-safe
sat_pubsub-0.4.0.dist-info/RECORD
